mersal_polling/__init__.py
mersal_polling/config.py
mersal_polling/default_poller.py
mersal_polling/error_handler_poller_wrapper.py
mersal_polling/message_completion_handler.py
mersal_polling/plugin.py
mersal_polling/poller.py
mersal_polling/poller_with_timeout.py
mersal_polling/py.typed
mersal_polling-0.1.0.dist-info/METADATA
mersal_polling-0.1.0.dist-info/WHEEL
mersal_polling-0.1.0.dist-info/RECORD
